{
  "vessel": {
    "vessel_name": "MV HMM MANILA",
    "former_name": "WANA BHUM",
    "owner": "HMM",
    "managers": "STX OCEAN SERVICE",
    "classification": "KR (Korean Registry)",
    "builder": "MITSUBISHI HEAVY INDUSTRIES LTD - SHIMONOSEKI, JAPAN",
    "hull_no": "1107",
    "call_sign": "D7LT",
    "imo_no": "9308663",
    "official_no": "4900 00036",
    "registry": "JEJU",
    "flag": "KOREA",
    "year_built": 2005,
    "keel_laying": "27 AUGUST 2004",
    "launching": "18 MARCH 2005",
    "delivery": "15 JUNE 2005",
    "complement": "24 PERSONS",
    "cargo_gears": "N/A",
    "sheet_date": "25-Dec-24",
    "loa_m": 194.9,
    "lbp_m": 186.0,
    "breadth_m": 30.6,
    "depth_m": 16.8,
    "draft_design_m": 11.4,
    "draft_scant_m": 11.425,
    "gross_t": 24181.0,
    "net_t": 9737.0,
    "dwt_t": 30832.0,
    "displacement_t": 40926.0,
    "light_weight_mt": 10094.0,
    "cargo_holds": 5,
    "hatch_pontoons": 24,
    "capacity_total_teu_nominal": 2378,
    "capacity_in_hold_teu": 806,
    "capacity_on_deck_teu": 1376,
    "reefer_points_total": 240,
    "reefer_points_deck": 240,
    "reefer_points_hold": 0,
    "reefer_voltage": "440V",
    "stackweight_ondeck_20_mt": 72,
    "stackweight_ondeck_40_mt": 100,
    "stackweight_hold_20_mt": 150,
    "stackweight_hold_40_mt": 210,
    "main_engine": "MITSUBISHI 7UEC68LSE",
    "engine_kw": 20580,
    "egcs_scrubber": true
  }
}